Workbook

Sheet Executive Summary
A1: AXIVEST — PORTFOLIO RISK & OPTIONS INTELLIGENCE
A2: Author: Kandala Guru Balaji | B.Tech CSBS (3rd Year) | Tagline: "See the risk. Test the downside."
A4: Avg Annual Volatility | B4: Worst Max Drawdown | C4: Assets Analysed | D4: Severe Stress Loss | E4: Options Strategies
A5: =AVERAGE('Risk Rankings'!C6:C15) | B5: =MIN('Risk Rankings'!D6:D16) | C5: 11 | D5: =ABS('Macro Stress Testing'!B23) | E5: 3
A7: Institutional Equity Universe & Benchmark Baseline
A8: Asset Name | B8: Ticker | C8: Sector | D8: Annualized Volatility | E8: Max Drawdown | F8: Risk Category
A9: Bharti Airtel | B9: BHARTIARTL.NS | C9: Telecom | D9: ='Risk Rankings'!C11 | E9: ='Risk Rankings'!D11 | F9: Moderate Risk
A10: HDFC Bank | B10: HDFCBANK.NS | C10: Banking | D10: ='Risk Rankings'!C13 | E10: ='Risk Rankings'!D13 | F10: Core Large-Cap
A11: ICICI Bank | B11: ICICIBANK.NS | C11: Banking | D11: ='Risk Rankings'!C15 | E11: ='Risk Rankings'!D15 | F11: Core Large-Cap
A12: Infosys | B12: INFY.NS | C12: Information Tech | D12: ='Risk Rankings'!C6 | E12: ='Risk Rankings'!D6 | F12: High Volatility
A13: ITC | B13: ITC.NS | C13: FMCG | D13: ='Risk Rankings'!C14 | E13: ='Risk Rankings'!D14 | F13: Defensive Value
A14: L&T | B14: LT.NS | C14: Infrastructure | D14: ='Risk Rankings'!C9 | E14: ='Risk Rankings'!D9 | F14: Industrial Growth
A15: M&M | B15: M&M.NS | C15: Automobile | D15: ='Risk Rankings'!C7 | E15: ='Risk Rankings'!D7 | F15: High Volatility
A16: NTPC | B16: NTPC.NS | C16: Energy & Utilities | D16: ='Risk Rankings'!C10 | E16: ='Risk Rankings'!D10 | F16: Utility Yield
A17: Reliance | B17: RELIANCE.NS | C17: Conglomerate | D17: ='Risk Rankings'!C12 | E17: ='Risk Rankings'!D12 | F17: Index Heavyweight
A18: TCS | B18: TCS.NS | C18: Information Tech | D18: ='Risk Rankings'!C8 | E18: ='Risk Rankings'!D8 | F18: Worst Drawdown
A19: NIFTY 50 | B19: ^NSEI | C19: Benchmark Index | D19: ='Risk Rankings'!C16 | E19: ='Risk Rankings'!D16 | F19: Benchmark Baseline

Sheet Risk Rankings
A1: ASSET RISK RANKINGS — VOLATILITY & MAXIMUM DRAWDOWN
A2: Quantitative evaluation over 497 trading days (October 2024 to October 2026)
A5: Asset Name | B5: Asset Type | C5: Annualized Volatility | D5: Maximum Drawdown | E5: Peak Date | F5: Trough Date | G5: Volatility Rank
A6: Infosys | B6: Equity | C6: 0.282009 | D6: -0.4817 | E6: 2024-12-13 | F6: 2026-07-01 | G6: =RANK(C6, $C$6:$C$16)
A7: M&M | B7: Equity | C7: 0.280473 | D7: -0.2689 | E7: 2026-01-02 | F7: 2026-10-08 | G7: =RANK(C7, $C$6:$C$16)
A8: TCS | B8: Equity | C8: 0.251016 | D8: -0.5268 | E8: 2024-12-13 | F8: 2026-07-01 | G8: =RANK(C8, $C$6:$C$16)
A9: L&T | B9: Equity | C9: 0.246283 | D9: -0.2435 | E9: 2026-02-23 | F9: 2026-03-23 | G9: =RANK(C9, $C$6:$C$16)
A10: NTPC | B10: Equity | C10: 0.212689 | D10: -0.2967 | E10: 2024-10-15 | F10: 2025-01-13 | G10: =RANK(C10, $C$6:$C$16)
A11: Bharti Airtel | B11: Equity | C11: 0.208961 | D11: -0.1877 | E11: 2025-11-21 | F11: 2026-05-12 | G11: =RANK(C11, $C$6:$C$16)
A12: Reliance | B12: Equity | C12: 0.207907 | D12: -0.2633 | E12: 2026-01-02 | F12: 2026-10-01 | G12: =RANK(C12, $C$6:$C$16)
A13: HDFC Bank | B13: Equity | C13: 0.198052 | D13: -0.3104 | E13: 2025-07-30 | F13: 2026-09-09 | G13: =RANK(C13, $C$6:$C$16)
A14: ITC | B14: Equity | C14: 0.194978 | D14: -0.4237 | E14: 2024-10-15 | F14: 2026-10-08 | G14: =RANK(C14, $C$6:$C$16)
A15: ICICI Bank | B15: Equity | C15: 0.184812 | D15: -0.1837 | E15: 2025-07-23 | F15: 2026-03-30 | G15: =RANK(C15, $C$6:$C$16)
A16: NIFTY 50 | B16: Index | C16: 0.131276 | D16: -0.1556 | E16: 2026-01-02 | F16: 2026-10-08 | G16: =RANK(C16, $C$6:$C$16)
A18: Average Equity Volatility | C18: =AVERAGE(C6:C15)
A19: Worst Historical Drawdown | D19: =MIN(D6:D16)

Sheet Macro Stress Testing
A1: PORTFOLIO MACRO STRESS TESTING SIMULATION
A2: Illustrative ₹100,000 Portfolio across 10 Equal-Weighted Equities (10% each = 100%)
A5: Stock | B5: Portfolio Weight | C5: Mild Stress Shock | D5: Moderate Stress Shock | E5: Severe Stress Shock
A6: TCS | B6: 0.1 | C6: -0.05 | D6: -0.12 | E6: -0.25
A7: Infosys | B7: 0.1 | C7: -0.05 | D7: -0.12 | E7: -0.25
A8: HDFC Bank | B8: 0.1 | C8: -0.04 | D8: -0.1 | E8: -0.22
A9: ICICI Bank | B9: 0.1 | C9: -0.04 | D9: -0.1 | E9: -0.22
A10: Reliance | B10: 0.1 | C10: -0.05 | D10: -0.12 | E10: -0.25
A11: NTPC | B11: 0.1 | C11: -0.03 | D11: -0.08 | E11: -0.18
A12: L&T | B12: 0.1 | C12: -0.05 | D12: -0.12 | E12: -0.25
A13: M&M | B13: 0.1 | C13: -0.06 | D13: -0.15 | E13: -0.3
A14: ITC | B14: 0.1 | C14: -0.03 | D14: -0.07 | E14: -0.15
A15: Bharti Airtel | B15: 0.1 | C15: -0.04 | D15: -0.09 | E15: -0.2
A16: Portfolio Weighted Return | B16: =SUM(B6:B15) | C16: =SUMPRODUCT($B$6:$B$15, C6:C15) | D16: =SUMPRODUCT($B$6:$B$15, D6:D15) | E16: =SUMPRODUCT($B$6:$B$15, E6:E15)
A19: Executive Scenario Capital Loss Summary
A20: Scenario | B20: Portfolio Return | C20: Portfolio Loss | D20: Starting Portfolio | E20: Post-Stress Residual Value
A21: Mild Stress | B21: =C16 | C21: =ABS(B21) | D21: 100000 | E21: =D21*(1+B21)
A22: Moderate Stress | B22: =D16 | C22: =ABS(B22) | D22: 100000 | E22: =D22*(1+B22)
A23: Severe Stress | B23: =E16 | C23: =ABS(B23) | D23: 100000 | E23: =D23*(1+B23)

Sheet Options Intelligence
A1: OPTIONS STRATEGY INTELLIGENCE & EXPIRATION PAYOFF
A2: Payoff curves across tested underlying strike ranges (₹700 to ₹1,300)
A4: Strategy Specifications & Risk Profile
A5: Strategy | B5: Description | C5: Net Premium Paid | D5: Max Profit | E5: Max Loss | F5: Lower Breakeven | G5: Upper Breakeven
A6: Bull Call Spread | B6: Limited-risk bullish play (Long 1000C / Short 1100C) | C6: 35 | D6: 65 | E6: -35 | F6: 1035 | G6: 1035
A7: Long Straddle | B7: Volatility breakout play (Long 1000C / Long 1000P) | C7: 105 | D7: Substantial | E7: -105 | F7: 895 | G7: 1105
A8: Iron Condor | B8: Range-bound credit play (850P/900P spread + 1100C/1150C spread) | C8: -23 | D8: 23 | E8: -27 | F8: 877 | G8: 1123
A11: Expiration Profit / Loss Schedule (₹ per unit)
A12: Spot Price at Expiry | B12: Bull Call Spread | C12: Long Straddle | D12: Iron Condor
A13: 700 | B13: =MAX(A13-1000, 0) - MAX(A13-1100, 0) - 35 | C13: =MAX(A13-1000, 0) + MAX(1000-A13, 0) - 105 | D13: =MAX(850-A13, 0) - MAX(900-A13, 0) - MAX(A13-1100, 0) + MAX(A13-1150, 0) + 23
A14: 725 | B14: =MAX(A14-1000, 0) - MAX(A14-1100, 0) - 35 | C14: =MAX(A14-1000, 0) + MAX(1000-A14, 0) - 105 | D14: =MAX(850-A14, 0) - MAX(900-A14, 0) - MAX(A14-1100, 0) + MAX(A14-1150, 0) + 23
A15: 750 | B15: =MAX(A15-1000, 0) - MAX(A15-1100, 0) - 35 | C15: =MAX(A15-1000, 0) + MAX(1000-A15, 0) - 105 | D15: =MAX(850-A15, 0) - MAX(900-A15, 0) - MAX(A15-1100, 0) + MAX(A15-1150, 0) + 23
A16: 775 | B16: =MAX(A16-1000, 0) - MAX(A16-1100, 0) - 35 | C16: =MAX(A16-1000, 0) + MAX(1000-A16, 0) - 105 | D16: =MAX(850-A16, 0) - MAX(900-A16, 0) - MAX(A16-1100, 0) + MAX(A16-1150, 0) + 23
A17: 800 | B17: =MAX(A17-1000, 0) - MAX(A17-1100, 0) - 35 | C17: =MAX(A17-1000, 0) + MAX(1000-A17, 0) - 105 | D17: =MAX(850-A17, 0) - MAX(900-A17, 0) - MAX(A17-1100, 0) + MAX(A17-1150, 0) + 23
A18: 825 | B18: =MAX(A18-1000, 0) - MAX(A18-1100, 0) - 35 | C18: =MAX(A18-1000, 0) + MAX(1000-A18, 0) - 105 | D18: =MAX(850-A18, 0) - MAX(900-A18, 0) - MAX(A18-1100, 0) + MAX(A18-1150, 0) + 23
A19: 850 | B19: =MAX(A19-1000, 0) - MAX(A19-1100, 0) - 35 | C19: =MAX(A19-1000, 0) + MAX(1000-A19, 0) - 105 | D19: =MAX(850-A19, 0) - MAX(900-A19, 0) - MAX(A19-1100, 0) + MAX(A19-1150, 0) + 23
A20: 875 | B20: =MAX(A20-1000, 0) - MAX(A20-1100, 0) - 35 | C20: =MAX(A20-1000, 0) + MAX(1000-A20, 0) - 105 | D20: =MAX(850-A20, 0) - MAX(900-A20, 0) - MAX(A20-1100, 0) + MAX(A20-1150, 0) + 23
A21: 900 | B21: =MAX(A21-1000, 0) - MAX(A21-1100, 0) - 35 | C21: =MAX(A21-1000, 0) + MAX(1000-A21, 0) - 105 | D21: =MAX(850-A21, 0) - MAX(900-A21, 0) - MAX(A21-1100, 0) + MAX(A21-1150, 0) + 23
A22: 925 | B22: =MAX(A22-1000, 0) - MAX(A22-1100, 0) - 35 | C22: =MAX(A22-1000, 0) + MAX(1000-A22, 0) - 105 | D22: =MAX(850-A22, 0) - MAX(900-A22, 0) - MAX(A22-1100, 0) + MAX(A22-1150, 0) + 23
A23: 950 | B23: =MAX(A23-1000, 0) - MAX(A23-1100, 0) - 35 | C23: =MAX(A23-1000, 0) + MAX(1000-A23, 0) - 105 | D23: =MAX(850-A23, 0) - MAX(900-A23, 0) - MAX(A23-1100, 0) + MAX(A23-1150, 0) + 23
A24: 975 | B24: =MAX(A24-1000, 0) - MAX(A24-1100, 0) - 35 | C24: =MAX(A24-1000, 0) + MAX(1000-A24, 0) - 105 | D24: =MAX(850-A24, 0) - MAX(900-A24, 0) - MAX(A24-1100, 0) + MAX(A24-1150, 0) + 23
... A37: 1300 | B37: =MAX(A37-1000, 0) - MAX(A37-1100, 0) - 35 | C37: =MAX(A37-1000, 0) + MAX(1000-A37, 0) - 105 | D37: =MAX(850-A37, 0) - MAX(900-A37, 0) - MAX(A37-1100, 0) + MAX(A37-1150, 0) + 23

Sheet Correlation Matrix
A1: PAIRWISE CORRELATION HEATMAP (DAILY RETURNS)
A2: Pearson correlation coefficients across 495 return observations (Aligned dates)
A4: Asset | B4: Bharti Airtel | C4: HDFC Bank | D4: ICICI Bank | E4: Infosys | F4: ITC | G4: L&T | H4: M&M | I4: NTPC | J4: Reliance | K4: TCS | L4: NIFTY 50
A5: Bharti Airtel | B5: 1 | C5: 0.2647 | D5: 0.2631 | E5: 0.1781 | F5: 0.2716 | G5: 0.2451 | H5: 0.3198 | I5: 0.1857 | J5: 0.3188 | K5: 0.1601 | L5: 0.4881
A6: HDFC Bank | B6: 0.2647 | C6: 1 | D6: 0.5038 | E6: 0.2057 | F6: 0.2534 | G6: 0.4593 | H6: 0.4084 | I6: 0.2325 | J6: 0.3887 | K6: 0.1933 | L6: 0.7091
A7: ICICI Bank | B7: 0.2631 | C7: 0.5038 | D7: 1 | E7: 0.1282 | F7: 0.2119 | G7: 0.4008 | H7: 0.4117 | I7: 0.273 | J7: 0.2773 | K7: 0.172 | L7: 0.6356
A8: Infosys | B8: 0.1781 | C8: 0.2057 | D8: 0.1282 | E8: 1 | F8: 0.1093 | G8: 0.2156 | H8: 0.2288 | I8: 0.0465 | J8: 0.1923 | K8: 0.7448 | L8: 0.417
A9: ITC | B9: 0.2716 | C9: 0.2534 | D9: 0.2119 | E9: 0.1093 | F9: 1 | G9: 0.2657 | H9: 0.2552 | I9: 0.1798 | J9: 0.3222 | K9: 0.1962 | L9: 0.4426
A10: L&T | B10: 0.2451 | C10: 0.4593 | D10: 0.4008 | E10: 0.2156 | F10: 0.2657 | G10: 1 | H10: 0.3932 | I10: 0.4249 | J10: 0.4431 | K10: 0.2582 | L10: 0.6988
A11: M&M | B11: 0.3198 | C11: 0.4084 | D11: 0.4117 | E11: 0.2288 | F11: 0.2552 | G11: 0.3932 | H11: 1 | I11: 0.2577 | J11: 0.3577 | K11: 0.2333 | L11: 0.6492
A12: NTPC | B12: 0.1857 | C12: 0.2325 | D12: 0.273 | E12: 0.0465 | F12: 0.1798 | G12: 0.4249 | H12: 0.2577 | I12: 1 | J12: 0.3715 | K12: 0.065 | L12: 0.4912
A13: Reliance | B13: 0.3188 | C13: 0.3887 | D13: 0.2773 | E13: 0.1923 | F13: 0.3222 | G13: 0.4431 | H13: 0.3577 | I13: 0.3715 | J13: 1 | K13: 0.2427 | L13: 0.6567
A14: TCS | B14: 0.1601 | C14: 0.1933 | D14: 0.172 | E14: 0.7448 | F14: 0.1962 | G14: 0.2582 | H14: 0.2333 | I14: 0.065 | J14: 0.2427 | K14: 1 | L14: 0.4399
A15: NIFTY 50 | B15: 0.4881 | C15: 0.7091 | D15: 0.6356 | E15: 0.417 | F15: 0.4426 | G15: 0.6988 | H15: 0.6492 | I15: 0.4912 | J15: 0.6567 | K15: 0.4399 | L15: 1
